{
  "groceries": [
    {
      "title": "omkar",
      "purchase": false,
      "id": 1
    },
    {
      "title": "omkar1243",
      "purchase": false,
      "id": 2
    },
    {
      "title": "hello",
      "purchase": false,
      "id": 3
    },
    {
      "title": "",
      "purchase": false,
      "id": 4
    },
    {
      "title": "aa",
      "purchase": false,
      "id": 5
    },
    {
      "title": "aabb",
      "purchase": false,
      "id": 6
    },
    {
      "title": "ffff",
      "purchase": false,
      "id": 7
    },
    {
      "title": "gggggggg",
      "purchase": false,
      "id": 8
    },
    {
      "title": "",
      "purchase": false,
      "id": 9
    }
  ]
}